knitvis/__init__.py
knitvis/chart.py
knitvis/double_knitting.py
knitvis/gui/controllers/__init__.py
knitvis/gui/controllers/base_controller.py
knitvis/gui/controllers/chart_controller.py
knitvis/gui/controllers/fabric_controller.py
knitvis/gui/dialogs/__init__.py
knitvis/gui/dialogs/background_image_dialog.py
knitvis/gui/dialogs/color_palette_dialog.py
knitvis/gui/dialogs/multiple_stitch_dialog.py
knitvis/gui/dialogs/new_chart_dialog.py
knitvis/gui/dialogs/preferences_dialog.py
knitvis/gui/dialogs/settings_dialog.py
knitvis/gui/dialogs/stitch_dialog.py
knitvis/gui/main.py
knitvis/gui/settings_manager.py
knitvis/gui/views/__init__.py
knitvis/gui/views/base_view.py
knitvis/gui/views/chart_debug.py
knitvis/gui/views/chart_view.py
knitvis/gui/views/fabric_view.py
knitvis/gui/widgets/__init__.py
knitvis/gui/widgets/chart_navigation.py
knitvis/gui/widgets/color_button.py
knitvis/palette.py
knitvis-0.1.0.dist-info/LICENSE
knitvis-0.1.0.dist-info/METADATA
knitvis-0.1.0.dist-info/WHEEL
knitvis-0.1.0.dist-info/RECORD
