Metadata-Version: 2.1
Name: knitvis
Version: 0.1.0
Summary: A knitting chart visualization tool
Author: Your Name
Author-email: your.email@example.com
Requires-Python: >=3.10,<4.0
Classifier: Programming Language :: Python :: 3
Classifier: Programming Language :: Python :: 3.10
Classifier: Programming Language :: Python :: 3.11
Requires-Dist: PyQt5 (>=5.15,<6.0)
Requires-Dist: matplotlib (>=3.5,<4.0)
Requires-Dist: numpy (>=1.22,<2.0)
Requires-Dist: pytest-qt (>=4.4.0,<5.0.0)
Requires-Dist: scipy (>=1.8,<2.0)
